qick/VERSION
qick/__init__.py
qick/asm_v1.py
qick/asm_v2.py
qick/averager_program.py
qick/helpers.py
qick/ip.py
qick/parser.py
qick/pyro.py
qick/pyro_cli.py
qick/qick.py
qick/qick_111.bit
qick/qick_111.hwh
qick/qick_216.bit
qick/qick_216.hwh
qick/qick_4x2.bit
qick/qick_4x2.hwh
qick/qick_asm.py
qick/rfboard.py
qick/streamer.py
qick/tprocv2_assembler.py
qick/drivers/__init__.py
qick/drivers/generator.py
qick/drivers/peripherals.py
qick/drivers/readout.py
qick/drivers/tproc.py
qick/drivers/xcom.py
qick/ipq_pynq_utils/setup.py
qick/ipq_pynq_utils/ipq_pynq_utils/__init__.py
qick/ipq_pynq_utils/ipq_pynq_utils/boards.py
qick/ipq_pynq_utils/ipq_pynq_utils/clock_models.py
qick/ipq_pynq_utils/ipq_pynq_utils/data_processing.py
qick/ipq_pynq_utils/ipq_pynq_utils/spidev.py
qick/ipq_pynq_utils/ipq_pynq_utils/data/lmk04828b_regdump_defaults.txt
qick/ipq_pynq_utils/ipq_pynq_utils/data/lmk04828b_regmap.json
qick/ipq_pynq_utils/ipq_pynq_utils/data/lmx2594_regmap.json
qick/ipq_pynq_utils/ipq_pynq_utils/data/xrfdc_cdefs.h
qick/ipq_pynq_utils/ipq_pynq_utils/data/clockFiles/LMX2594_REF-245M76__OUT-0204M80_10172019_I_D.txt
qick/ipq_pynq_utils/ipq_pynq_utils/data/clockFiles/LMX2594_REF-245M76__OUT-0245M76_10172019_I_D.txt
qick/ipq_pynq_utils/ipq_pynq_utils/data/clockFiles/LMX2594_REF-245M76__OUT-0491M52_10172019_I_D.txt
qick/ipq_pynq_utils/ipq_pynq_utils/data/clockFiles/LMX2594_REF-245M76__OUT-1024M00_11052019_D.txt
qick/ipq_pynq_utils/ipq_pynq_utils/data/clockFiles/LMX2594_REF-245M76__OUT-1966M08_10172019_I_D.txt
qick/ipq_pynq_utils/ipq_pynq_utils/data/clockFiles/LMX2594_REF-245M76__OUT-2211M84_10172019_I_D.txt
qick/ipq_pynq_utils/ipq_pynq_utils/data/clockFiles/LMX2594_REF-245M76__OUT-2457M60_10172019_I_D.txt
qick/ipq_pynq_utils/ipq_pynq_utils/data/clockFiles/LMX2594_REF-245M76__OUT-3072M00_10172019_I_D.txt
qick/ipq_pynq_utils/ipq_pynq_utils/data/clockFiles/LMX2594_REF-245M76__OUT-3932M16_10172019_I.txt
qick-0.2.388.dist-info/licenses/LICENSE
qick-0.2.388.dist-info/METADATA
qick-0.2.388.dist-info/WHEEL
qick-0.2.388.dist-info/top_level.txt
qick-0.2.388.dist-info/RECORD
