Metadata-Version: 2.4
Name: qick
Version: 0.2.388
Summary: Quantum Instrumentation Controller Kit software library
Home-page: https://github.com/openquantumhardware/qick
Author: Open Quantum Hardware
Author-email: openquantumhardware@gmail.com
Project-URL: Source, https://github.com/openquantumhardware/qick
Project-URL: Documentation, https://qick-docs.readthedocs.io/latest/
Project-URL: Tracker, https://github.com/openquantumhardware/qick/issues
Classifier: Development Status :: 3 - Alpha
Classifier: Intended Audience :: Developers
Classifier: Topic :: Software Development :: Build Tools
Classifier: License :: OSI Approved :: MIT License
Classifier: Programming Language :: Python :: 3
Classifier: Programming Language :: Python :: 3.6
Classifier: Programming Language :: Python :: 3.7
Classifier: Programming Language :: Python :: 3.8
Classifier: Programming Language :: Python :: 3.9
Classifier: Programming Language :: Python :: 3 :: Only
Requires-Python: >=3.6, <4
License-File: LICENSE
Requires-Dist: numpy
Requires-Dist: pynq<3.1,>=2.6; platform_machine == "aarch64" or platform_machine == "armv7l"
Requires-Dist: tqdm
Provides-Extra: full
Requires-Dist: pyro4; extra == "full"
Dynamic: author
Dynamic: author-email
Dynamic: classifier
Dynamic: description
Dynamic: description-content-type
Dynamic: home-page
Dynamic: license-file
Dynamic: project-url
Dynamic: provides-extra
Dynamic: requires-dist
Dynamic: requires-python
Dynamic: summary
